LICENSE
MANIFEST.in
README
VERSION
setup.py
cutil/cutil.cpp
cutil/cutil.hpp
src/colorcorrect/__init__.py
src/colorcorrect/algorithm.py
src/colorcorrect/util.py
src/colorcorrect.egg-info/PKG-INFO
src/colorcorrect.egg-info/SOURCES.txt
src/colorcorrect.egg-info/dependency_links.txt
src/colorcorrect.egg-info/requires.txt
src/colorcorrect.egg-info/top_level.txt