Metadata-Version: 1.0
Name: colorcorrect
Version: 0.7
Summary: imprement some of color correction algorithms
Home-page: http://www.bitbucket.org/aihara/colorcorrect
Author: Shunsuke Aihara
Author-email: s.aihara@gmail.com
License: MIT License
Keywords: image-processing computer-vision
Platform: UNKNOWN
